airflow_examples_connector/__init__.py
airflow_examples_connector/_version.py
airflow_examples_connector/elyra-airflow-catalog.json
airflow_examples_connector/examples_connector.py
airflow_examples_connector/examples_schema_provider.py
airflow_examples_connector/resources/bash_operator.py
airflow_examples_connector/resources/email_operator.py
airflow_examples_connector/resources/http_operator.py
airflow_examples_connector/resources/slack_operator.py
airflow_examples_connector/resources/spark_sql_operator.py
airflow_examples_connector/resources/spark_submit_operator.py
elyra_examples_airflow_catalog-0.1.0.dist-info/METADATA
elyra_examples_airflow_catalog-0.1.0.dist-info/WHEEL
elyra_examples_airflow_catalog-0.1.0.dist-info/entry_points.txt
elyra_examples_airflow_catalog-0.1.0.dist-info/top_level.txt
elyra_examples_airflow_catalog-0.1.0.dist-info/RECORD
